matrix/__init__.py
PyMat-0.0.2.dist-info/LICENSE
PyMat-0.0.2.dist-info/METADATA
PyMat-0.0.2.dist-info/WHEEL
PyMat-0.0.2.dist-info/top_level.txt
PyMat-0.0.2.dist-info/RECORD
