Metadata-Version: 2.1
Name: PyMat
Version: 0.0.2
Summary: A mathematics matrix module for Python3
Home-page: https://github.com/baely/matrix
Author: baely
Author-email: me@baely.dev
License: UNKNOWN
Platform: UNKNOWN
Classifier: Programming Language :: Python :: 3
Classifier: License :: OSI Approved :: MIT License
Classifier: Operating System :: OS Independent
Requires-Python: >=3.6
